napari_hippo/__init__.py
napari_hippo/_caterpillarWidget.py
napari_hippo/_crunchyTools.py
napari_hippo/_fieldTools.py
napari_hippo/_guiBase.py
napari_hippo/_hyliteTools.py
napari_hippo/_ioTools.py
napari_hippo/_reader.py
napari_hippo/_sample_data.py
napari_hippo/_util.py
napari_hippo/_writer.py
napari_hippo/napari.yaml
napari_hippo/_tests/__init__.py
napari_hippo/_tests/test_Caterpillar.py
napari_hippo/_tests/test_CrunchyTools.py
napari_hippo/_tests/test_HyliteTools.py
napari_hippo/_tests/test_IOTools.py
napari_hippo/_tests/test_reader.py
napari_hippo/_tests/test_sample_data.py
napari_hippo/_tests/test_writer.py
napari_hippo/testdata/__init__.py
napari_hippo/testdata/block1.dat
napari_hippo/testdata/block1.hdr
napari_hippo/testdata/block1.png
napari_hippo/testdata/block2.dat
napari_hippo/testdata/block2.hdr
napari_hippo/testdata/block2.png
napari_hippo/testdata/image.dat
napari_hippo/testdata/image.hdr
napari_hippo-0.2.0.dist-info/LICENSE
napari_hippo-0.2.0.dist-info/METADATA
napari_hippo-0.2.0.dist-info/WHEEL
napari_hippo-0.2.0.dist-info/entry_points.txt
napari_hippo-0.2.0.dist-info/top_level.txt
napari_hippo-0.2.0.dist-info/RECORD
